nonebot_plugin_playwright/__init__.py
nonebot_plugin_playwright/browser.py
nonebot_plugin_playwright/config.py
nonebot_plugin_playwright/tool.py
nonebot_plugin_playwright/tool.pyi
nonebot_plugin_playwright-0.2.0.dist-info/LICENSE
nonebot_plugin_playwright-0.2.0.dist-info/METADATA
nonebot_plugin_playwright-0.2.0.dist-info/WHEEL
nonebot_plugin_playwright-0.2.0.dist-info/RECORD
