Metadata-Version: 2.1
Name: nonebot-plugin-playwright
Version: 0.2.0
Summary: NoneBot Playwright插件
License: MIT
Author: eya46
Author-email: 61458340+eya46@users.noreply.github.com
Requires-Python: >=3.9,<4.0
Classifier: License :: OSI Approved :: MIT License
Classifier: Programming Language :: Python :: 3
Classifier: Programming Language :: Python :: 3.9
Classifier: Programming Language :: Python :: 3.10
Classifier: Programming Language :: Python :: 3.11
Classifier: Programming Language :: Python :: 3.12
Provides-Extra: localstore
Requires-Dist: nonebot-plugin-localstore (>=0.7.1) ; extra == "localstore"
Requires-Dist: nonebot2 (>=2.2.0)
Requires-Dist: playwright (>=1.0.0,<2.0.0)
